llm_fallbacks/__init__.py
llm_fallbacks/__main__.py
llm_fallbacks/config.py
llm_fallbacks/core.py
llm_fallbacks/filter_litellm.py
llm_fallbacks/generate_configs.py
llm_fallbacks-0.1.0.dist-info/licenses/LICENSE
tests/__init__.py
tests/test_core.py
llm_fallbacks-0.1.0.dist-info/METADATA
llm_fallbacks-0.1.0.dist-info/WHEEL
llm_fallbacks-0.1.0.dist-info/top_level.txt
llm_fallbacks-0.1.0.dist-info/RECORD
