Metadata-Version: 2.4
Name: llm-fallbacks
Version: 0.1.0
Summary: A comprehensive Python library for managing fallback mechanisms for Large Language Model (LLM) API calls using LiteLLM
Author-email: Boden Crouch <boden.crouch@gmail.com>
Maintainer-email: Boden Crouch <boden.crouch@gmail.com>
License: Business Source License 1.1
Project-URL: Homepage, https://github.com/bodencrouch/llm-fallbacks
Project-URL: Documentation, https://github.com/bodencrouch/llm-fallbacks
Project-URL: Repository, https://github.com/bodencrouch/llm-fallbacks
Project-URL: Issues, https://github.com/bodencrouch/llm-fallbacks/issues
Project-URL: Changelog, https://github.com/bodencrouch/llm-fallbacks/releases
Keywords: llm,ai,fallbacks,litellm,language-models,api,fallback-strategies
Classifier: Development Status :: 4 - Beta
Classifier: Intended Audience :: Developers
Classifier: Intended Audience :: Information Technology
Classifier: License :: Other/Proprietary License
Classifier: Natural Language :: English
Classifier: Operating System :: OS Independent
Classifier: Programming Language :: Python :: 3
Classifier: Programming Language :: Python :: 3.12
Classifier: Programming Language :: Python :: 3.13
Classifier: Topic :: Scientific/Engineering :: Artificial Intelligence
Classifier: Topic :: Software Development :: Libraries :: Python Modules
Classifier: Topic :: Text Processing :: Linguistic
Requires-Python: >=3.12
License-File: LICENSE
Requires-Dist: requests>=2.31.0
Requires-Dist: pandas>=2.0.0
Requires-Dist: numpy>=1.24.0
Requires-Dist: pyyaml>=6.0
Requires-Dist: litellm>=1.0.0
Provides-Extra: dev
Requires-Dist: pytest>=8.4.1; extra == "dev"
Requires-Dist: pytest-cov>=5.0.0; extra == "dev"
Requires-Dist: pytest-benchmark>=4.0.0; extra == "dev"
Requires-Dist: ruff>=0.6.2; extra == "dev"
Requires-Dist: black>=24.8.0; extra == "dev"
Requires-Dist: isort>=5.13.2; extra == "dev"
Requires-Dist: mypy>=1.11.1; extra == "dev"
Requires-Dist: pre-commit>=3.8.0; extra == "dev"
Requires-Dist: build>=1.2.1; extra == "dev"
Requires-Dist: twine>=5.1.0; extra == "dev"
Dynamic: license-file
